metacat/__init__.py
metacat/version.py
metacat/auth/__init__.py
metacat/auth/auth_core.py
metacat/auth/authenticators.py
metacat/auth/dbuser.py
metacat/common/__init__.py
metacat/common/attributes.py
metacat/common/auth_client.py
metacat/common/dbbase.py
metacat/common/exceptions.py
metacat/common/http_client.py
metacat/common/meta_dnf.py
metacat/common/password_hash.py
metacat/common/rfc2617.py
metacat/common/signed_token_jwt.py
metacat/common/token_lib.py
metacat/common/transaction.py
metacat/common/trees.py
metacat/db/__init__.py
metacat/db/common.py
metacat/db/dbobjects2.py
metacat/db/drop_all.sql
metacat/db/param_category.py
metacat/db/schema.sql
metacat/logs/__init__.py
metacat/logs/log_file.py
metacat/logs/logs.py
metacat/mql/__init__.py
metacat/mql/meta_evaluator.py
metacat/mql/mql10.py
metacat/mql/query_executor.py
metacat/mql/sql_converter.py
metacat/mql/grammar/__init__.py
metacat/mql/grammar/combine.py
metacat/mql/grammar/common.py
metacat/mql/grammar/dataset_query.py
metacat/mql/grammar/file_query.py
metacat/mql/grammar/query_query.py
metacat/ui/common.py
metacat/ui/foo.py
metacat/ui/metacat_admin.py
metacat/ui/metacat_auth.py
metacat/ui/metacat_category.py
metacat/ui/metacat_config.py
metacat/ui/metacat_dataset.py
metacat/ui/metacat_file.py
metacat/ui/metacat_mql.py
metacat/ui/metacat_named_query.py
metacat/ui/metacat_namespace.py
metacat/ui/metacat_query.py
metacat/ui/metacat_ui.py
metacat/ui/mql.py
metacat/ui/cli/__init__.py
metacat/ui/cli/cli.py
metacat/util/__init__.py
metacat/util/generators.py
metacat/util/object_spec.py
metacat/util/py3.py
metacat/util/timelib.py
metacat/util/trace.py
metacat/util/utils.py
metacat/util/validation.py
metacat/webapi/__init__.py
metacat/webapi/webapi.py
metacat_client-4.1.2.dist-info/licenses/LICENSE
metacat_client-4.1.2.dist-info/METADATA
metacat_client-4.1.2.dist-info/WHEEL
metacat_client-4.1.2.dist-info/entry_points.txt
metacat_client-4.1.2.dist-info/top_level.txt
metacat_client-4.1.2.dist-info/RECORD
