Metadata-Version: 2.4
Name: metacat-client
Version: 4.1.2
Summary: MetaCat is a general purpose metadata database. This package is the client side portion of the product.
Home-page: https://github.com/fermitools/metacat
Author: Marc Mengel, Igor Mandrichenko
Author-email: mengel@fnal.gov
License: BSD 3-clause
Keywords: metadata,data management,database,web service
License-File: LICENSE
Requires-Dist: pyjwt
Requires-Dist: requests
Requires-Dist: pythreader>=2.8.0
Requires-Dist: lark
Dynamic: author
Dynamic: author-email
Dynamic: home-page
Dynamic: keywords
Dynamic: license
Dynamic: license-file
Dynamic: requires-dist
Dynamic: summary
